{
    "features": [
        {
            "properties": {
                "lat": 38.87592037952956,
                "lon": -76.99900089596306,
                "mode": "bicycle",
                "type": "time",
                "range": 600,
                "route_type": "less_maneuvers",
                "traffic": "approximated",
                "id": "c691da77813f0c1602b920d59ab108cc"
            },
            "geometry": {
                "coordinates": [
                    [
                        [
                            [
                                -76.998001,
                                38.893076
                            ],
                            [
                                -76.998114,
                                38.893033
                            ],
                            [
                                -76.998486,
                                38.89292
                            ],
                            [
                                -76.998882,
                                38.892801
                            ],
                            [
                                -76.999001,
                                38.892721
                            ],
                            [
                                -76.999489,
                                38.892433
                            ],
                            [
                                -76.999504,
                                38.892423
                            ],
                            [
                                -77.000001,
                                38.8922
                            ],
                            [
                                -77.000105,
                                38.892024
                            ],
                            [
                                -77.00025,
                                38.89192
                            ],
                            [
                                -77.000552,
                                38.891472
                            ],
                            [
                                -77.000657,
                                38.891264
                            ],
                            [
                                -77.000846,
                                38.89092
                            ],
                            [
                                -77.000923,
                                38.890842
                            ],
                            [
                                -77.001001,
                                38.890773
                            ],
                            [
                                -77.001105,
                                38.890817
                            ],
                            [
                                -77.001352,
                                38.89092
                            ],
                            [
                                -77.001732,
                                38.89119
                            ],
                            [
                                -77.002001,
                                38.891285
                            ],
                            [
                                -77.002191,
                                38.891111
                            ],
                            [
                                -77.00237,
                                38.89092
                            ],
                            [
                                -77.002622,
                                38.890541
                            ],
                            [
                                -77.002618,
                                38.890303
                            ],
                            [
                                -77.002725,
                                38.88992
                            ],
                            [
                                -77.002797,
                                38.889717
                            ],
                            [
                                -77.003001,
                                38.889136
                            ],
                            [
                                -77.0031,
                                38.88902
                            ],
                            [
                                -77.003212,
                                38.88892
                            ],
                            [
                                -77.003841,
                                38.888761
                            ],
                            [
                                -77.004001,
                                38.888731
                            ],
                            [
                                -77.004348,
                                38.888268
                            ],
                            [
                                -77.004606,
                                38.88792
                            ],
                            [
                                -77.004513,
                                38.887433
                            ],
                            [
                                -77.004511,
                                38.887411
                            ],
                            [
                                -77.004402,
                                38.88692
                            ],
                            [
                                -77.004718,
                                38.886637
                            ],
                            [
                                -77.005001,
                                38.886499
                            ],
                            [
                                -77.005271,
                                38.88665
                            ],
                            [
                                -77.005462,
                                38.88692
                            ],
                            [
                                -77.005576,
                                38.887345
                            ],
                            [
                                -77.006001,
                                38.887758
                            ],
                            [
                                -77.00639,
                                38.887309
                            ],
                            [
                                -77.006539,
                                38.88692
                            ],
                            [
                                -77.006724,
                                38.886644
                            ],
                            [
                                -77.007001,
                                38.886465
                            ],
                            [
                                -77.007391,
                                38.886531
                            ],
                            [
                                -77.007785,
                                38.88692
                            ],
                            [
                                -77.007853,
                                38.887068
                            ],
                            [
                                -77.008001,
                                38.887225
                            ],
                            [
                                -77.008133,
                                38.887052
                            ],
                            [
                                -77.008217,
                                38.88692
                            ],
                            [
                                -77.008527,
                                38.886446
                            ],
                            [
                                -77.009001,
                                38.88614
                            ],
                            [
                                -77.009147,
                                38.886067
                            ],
                            [
                                -77.00922,
                                38.88592
                            ],
                            [
                                -77.009733,
                                38.885652
                            ],
                            [
                                -77.010001,
                                38.885595
                            ],
                            [
                                -77.010247,
                                38.885674
                            ],
                            [
                                -77.010448,
                                38.88592
                            ],
                            [
                                -77.010632,
                                38.886289
                            ],
                            [
                                -77.011001,
                                38.886473
                            ],
                            [
                                -77.011327,
                                38.886594
                            ],
                            [
                                -77.01157,
                                38.88692
                            ],
                            [
                                -77.01169,
                                38.887231
                            ],
                            [
                                -77.012001,
                                38.88747
                            ],
                            [
                                -77.012365,
                                38.887556
                            ],
                            [
                                -77.012836,
                                38.88792
                            ],
                            [
                                -77.012931,
                                38.88799
                            ],
                            [
                                -77.013001,
                                38.888024
                            ],
                            [
                                -77.013121,
                                38.88804
                            ],
                            [
                                -77.013808,
                                38.888113
                            ],
                            [
                                -77.014001,
                                38.888142
                            ],
                            [
                                -77.014216,
                                38.888135
                            ],
                            [
                                -77.014789,
                                38.88792
                            ],
                            [
                                -77.014768,
                                38.887687
                            ],
                            [
                                -77.014629,
                                38.887293
                            ],
                            [
                                -77.01461,
                                38.88692
                            ],
                            [
                                -77.01445,
                                38.886471
                            ],
                            [
                                -77.014335,
                                38.886254
                            ],
                            [
                                -77.014181,
                                38.88592
                            ],
                            [
                                -77.014073,
                                38.885848
                            ],
                            [
                                -77.014001,
                                38.885744
                            ],
                            [
                                -77.013752,
                                38.885672
                            ],
                            [
                                -77.013453,
                                38.885468
                            ],
                            [
                                -77.013001,
                                38.88543
                            ],
                            [
                                -77.012705,
                                38.885217
                            ],
                            [
                                -77.012568,
                                38.88492
                            ],
                            [
                                -77.012605,
                                38.884524
                            ],
                            [
                                -77.012596,
                                38.884325
                            ],
                            [
                                -77.012625,
                                38.88392
                            ],
                            [
                                -77.012553,
                                38.883473
                            ],
                            [
                                -77.012528,
                                38.883393
                            ],
                            [
                                -77.012476,
                                38.88292
                            ],
                            [
                                -77.012496,
                                38.882425
                            ],
                            [
                                -77.012001,
                                38.882026
                            ],
                            [
                                -77.011896,
                                38.882025
                            ],
                            [
                                -77.011203,
                                38.882123
                            ],
                            [
                                -77.011001,
                                38.882121
                            ],
                            [
                                -77.010883,
                                38.882038
                            ],
                            [
                                -77.010834,
                                38.88192
                            ],
                            [
                                -77.010577,
                                38.881496
                            ],
                            [
                                -77.010565,
                                38.881356
                            ],
                            [
                                -77.010461,
                                38.881381
                            ],
                            [
                                -77.010001,
                                38.881214
                            ],
                            [
                                -77.009833,
                                38.881088
                            ],
                            [
                                -77.009776,
                                38.88092
                            ],
                            [
                                -77.009785,
                                38.880704
                            ],
                            [
                                -77.009785,
                                38.880137
                            ],
                            [
                                -77.009792,
                                38.87992
                            ],
                            [
                                -77.009861,
                                38.87978
                            ],
                            [
                                -77.010001,
                                38.879699
                            ],
                            [
                                -77.010175,
                                38.879746
                            ],
                            [
                                -77.010382,
                                38.87992
                            ],
                            [
                                -77.010565,
                                38.880356
                            ],
                            [
                                -77.011001,
                                38.880657
                            ],
                            [
                                -77.011148,
                                38.880773
                            ],
                            [
                                -77.011245,
                                38.88092
                            ],
                            [
                                -77.011406,
                                38.881325
                            ],
                            [
                                -77.011391,
                                38.881531
                            ],
                            [
                                -77.011712,
                                38.881631
                            ],
                            [
                                -77.012001,
                                38.881826
                            ],
                            [
                                -77.012083,
                                38.881839
                            ],
                            [
                                -77.012389,
                                38.88192
                            ],
                            [
                                -77.012525,
                                38.882396
                            ],
                            [
                                -77.013001,
                                38.882065
                            ],
                            [
                                -77.013173,
                                38.882093
                            ],
                            [
                                -77.013784,
                                38.882137
                            ],
                            [
                                -77.014001,
                                38.882181
                            ],
                            [
                                -77.014316,
                                38.882235
                            ],
                            [
                                -77.014628,
                                38.882293
                            ],
                            [
                                -77.015001,
                                38.882355
                            ],
                            [
                                -77.015458,
                                38.882377
                            ],
                            [
                                -77.015551,
                                38.88237
                            ],
                            [
                                -77.016001,
                                38.882399
                            ],
                            [
                                -77.016483,
                                38.882402
                            ],
                            [
                                -77.016561,
                                38.882361
                            ],
                            [
                                -77.017001,
                                38.882372
                            ],
                            [
                                -77.017466,
                                38.882455
                            ],
                            [
                                -77.017541,
                                38.882461
                            ],
                            [
                                -77.018001,
                                38.88253
                            ],
                            [
                                -77.018225,
                                38.882144
                            ],
                            [
                                -77.018386,
                                38.88192
                            ],
                            [
                                -77.018581,
                                38.8815
                            ],
                            [
                                -77.018652,
                                38.881269
                            ],
                            [
                                -77.018783,
                                38.88092
                            ],
                            [
                                -77.018823,
                                38.880742
                            ],
                            [
                                -77.018916,
                                38.880005
                            ],
                            [
                                -77.018932,
                                38.87992
                            ],
                            [
                                -77.018956,
                                38.879875
                            ],
                            [
                                -77.019001,
                                38.879839
                            ],
                            [
                                -77.019086,
                                38.879835
                            ],
                            [
                                -77.019254,
                                38.87992
                            ],
                            [
                                -77.019601,
                                38.88032
                            ],
                            [
                                -77.020001,
                                38.880492
                            ],
                            [
                                -77.020307,
                                38.880227
                            ],
                            [
                                -77.020809,
                                38.87992
                            ],
                            [
                                -77.020893,
                                38.879813
                            ],
                            [
                                -77.021001,
                                38.879641
                            ],
                            [
                                -77.021193,
                                38.879729
                            ],
                            [
                                -77.021594,
                                38.879513
                            ],
                            [
                                -77.022001,
                                38.879548
                            ],
                            [
                                -77.022499,
                                38.879419
                            ],
                            [
                                -77.022503,
                                38.879419
                            ],
                            [
                                -77.023001,
                                38.879323
                            ],
                            [
                                -77.023458,
                                38.879378
                            ],
                            [
                                -77.023694,
                                38.879228
                            ],
                            [
                                -77.024001,
                                38.879741
                            ],
                            [
                                -77.024068,
                                38.878987
                            ],
                            [
                                -77.024046,
                                38.87892
                            ],
                            [
                                -77.024039,
                                38.878882
                            ],
                            [
                                -77.024001,
                                38.878858
                            ],
                            [
                                -77.023917,
                                38.878836
                            ],
                            [
                                -77.02329,
                                38.878631
                            ],
                            [
                                -77.023001,
                                38.878569
                            ],
                            [
                                -77.022614,
                                38.878307
                            ],
                            [
                                -77.022501,
                                38.87792
                            ],
                            [
                                -77.022148,
                                38.877774
                            ],
                            [
                                -77.022001,
                                38.877742
                            ],
                            [
                                -77.021597,
                                38.877516
                            ],
                            [
                                -77.021418,
                                38.877504
                            ],
                            [
                                -77.021431,
                                38.877351
                            ],
                            [
                                -77.021242,
                                38.87692
                            ],
                            [
                                -77.021239,
                                38.876683
                            ],
                            [
                                -77.021198,
                                38.876117
                            ],
                            [
                                -77.021194,
                                38.87592
                            ],
                            [
                                -77.021269,
                                38.875652
                            ],
                            [
                                -77.021228,
                                38.875148
                            ],
                            [
                                -77.021418,
                                38.87492
                            ],
                            [
                                -77.021192,
                                38.874729
                            ],
                            [
                                -77.021001,
                                38.874744
                            ],
                            [
                                -77.020819,
                                38.874738
                            ],
                            [
                                -77.020192,
                                38.874729
                            ],
                            [
                                -77.020001,
                                38.874723
                            ],
                            [
                                -77.019807,
                                38.874727
                            ],
                            [
                                -77.019237,
                                38.874684
                            ],
                            [
                                -77.019001,
                                38.874688
                            ],
                            [
                                -77.018506,
                                38.874415
                            ],
                            [
                                -77.018214,
                                38.87392
                            ],
                            [
                                -77.018233,
                                38.873689
                            ],
                            [
                                -77.018278,
                                38.873197
                            ],
                            [
                                -77.0183,
                                38.87292
                            ],
                            [
                                -77.01834,
                                38.872581
                            ],
                            [
                                -77.018351,
                                38.87227
                            ],
                            [
                                -77.018401,
                                38.87192
                            ],
                            [
                                -77.018229,
                                38.871693
                            ],
                            [
                                -77.018001,
                                38.871573
                            ],
                            [
                                -77.017627,
                                38.871547
                            ],
                            [
                                -77.017391,
                                38.87153
                            ],
                            [
                                -77.017001,
                                38.871503
                            ],
                            [
                                -77.016576,
                                38.871495
                            ],
                            [
                                -77.016437,
                                38.871485
                            ],
                            [
                                -77.016001,
                                38.871478
                            ],
                            [
                                -77.015542,
                                38.871462
                            ],
                            [
                                -77.015464,
                                38.871457
                            ],
                            [
                                -77.015001,
                                38.871441
                            ],
                            [
                                -77.014664,
                                38.871258
                            ],
                            [
                                -77.01448,
                                38.87092
                            ],
                            [
                                -77.014425,
                                38.870496
                            ],
                            [
                                -77.014304,
                                38.870223
                            ],
                            [
                                -77.014235,
                                38.86992
                            ],
                            [
                                -77.014243,
                                38.869679
                            ],
                            [
                                -77.014188,
                                38.869107
                            ],
                            [
                                -77.014196,
                                38.86892
                            ],
                            [
                                -77.014191,
                                38.86873
                            ],
                            [
                                -77.014032,
                                38.867952
                            ],
                            [
                                -77.014031,
                                38.86792
                            ],
                            [
                                -77.014024,
                                38.867898
                            ],
                            [
                                -77.014001,
                                38.867797
                            ],
                            [
                                -77.013955,
                                38.867874
                            ],
                            [
                                -77.013955,
                                38.86792
                            ],
                            [
                                -77.013945,
                                38.867977
                            ],
                            [
                                -77.013733,
                                38.868652
                            ],
                            [
                                -77.013697,
                                38.86892
                            ],
                            [
                                -77.013393,
                                38.869313
                            ],
                            [
                                -77.013001,
                                38.869426
                            ],
                            [
                                -77.012683,
                                38.869238
                            ],
                            [
                                -77.012506,
                                38.86892
                            ],
                            [
                                -77.012463,
                                38.868458
                            ],
                            [
                                -77.012444,
                                38.868364
                            ],
                            [
                                -77.012394,
                                38.86792
                            ],
                            [
                                -77.012393,
                                38.867528
                            ],
                            [
                                -77.012284,
                                38.867204
                            ],
                            [
                                -77.012282,
                                38.86692
                            ],
                            [
                                -77.012186,
                                38.866736
                            ],
                            [
                                -77.012001,
                                38.866417
                            ],
                            [
                                -77.011635,
                                38.866286
                            ],
                            [
                                -77.011223,
                                38.866143
                            ],
                            [
                                -77.011001,
                                38.866064
                            ],
                            [
                                -77.010541,
                                38.86646
                            ],
                            [
                                -77.010404,
                                38.866518
                            ],
                            [
                                -77.010001,
                                38.866731
                            ],
                            [
                                -77.009869,
                                38.866788
                            ],
                            [
                                -77.009482,
                                38.86692
                            ],
                            [
                                -77.0092,
                                38.86712
                            ],
                            [
                                -77.009001,
                                38.867205
                            ],
                            [
                                -77.008787,
                                38.867707
                            ],
                            [
                                -77.008749,
                                38.86792
                            ],
                            [
                                -77.008285,
                                38.868205
                            ],
                            [
                                -77.008001,
                                38.868251
                            ],
                            [
                                -77.007665,
                                38.868256
                            ],
                            [
                                -77.007337,
                                38.868256
                            ],
                            [
                                -77.007001,
                                38.868262
                            ],
                            [
                                -77.006723,
                                38.868198
                            ],
                            [
                                -77.006384,
                                38.86792
                            ],
                            [
                                -77.006256,
                                38.867665
                            ],
                            [
                                -77.006001,
                                38.867538
                            ],
                            [
                                -77.00554,
                                38.86746
                            ],
                            [
                                -77.005479,
                                38.867442
                            ],
                            [
                                -77.005001,
                                38.867382
                            ],
                            [
                                -77.004585,
                                38.867336
                            ],
                            [
                                -77.004311,
                                38.86723
                            ],
                            [
                                -77.004001,
                                38.867174
                            ],
                            [
                                -77.003779,
                                38.867142
                            ],
                            [
                                -77.0035,
                                38.86692
                            ],
                            [
                                -77.003205,
                                38.866716
                            ],
                            [
                                -77.003001,
                                38.866377
                            ],
                            [
                                -77.002592,
                                38.866511
                            ],
                            [
                                -77.002029,
                                38.86692
                            ],
                            [
                                -77.002015,
                                38.866935
                            ],
                            [
                                -77.002001,
                                38.866953
                            ],
                            [
                                -77.001787,
                                38.867135
                            ],
                            [
                                -77.001458,
                                38.867377
                            ],
                            [
                                -77.001436,
                                38.867485
                            ],
                            [
                                -77.001234,
                                38.86792
                            ],
                            [
                                -77.001784,
                                38.868137
                            ],
                            [
                                -77.002001,
                                38.868114
                            ],
                            [
                                -77.002287,
                                38.868206
                            ],
                            [
                                -77.002617,
                                38.868305
                            ],
                            [
                                -77.003001,
                                38.86844
                            ],
                            [
                                -77.003496,
                                38.868426
                            ],
                            [
                                -77.003504,
                                38.868424
                            ],
                            [
                                -77.004001,
                                38.868415
                            ],
                            [
                                -77.004313,
                                38.868608
                            ],
                            [
                                -77.004443,
                                38.86892
                            ],
                            [
                                -77.004629,
                                38.869292
                            ],
                            [
                                -77.005001,
                                38.869478
                            ],
                            [
                                -77.005409,
                                38.869513
                            ],
                            [
                                -77.005593,
                                38.869513
                            ],
                            [
                                -77.006001,
                                38.869542
                            ],
                            [
                                -77.00636,
                                38.869562
                            ],
                            [
                                -77.006642,
                                38.869562
                            ],
                            [
                                -77.007001,
                                38.869579
                            ],
                            [
                                -77.007214,
                                38.869707
                            ],
                            [
                                -77.007292,
                                38.86992
                            ],
                            [
                                -77.007168,
                                38.870088
                            ],
                            [
                                -77.007001,
                                38.870153
                            ],
                            [
                                -77.006535,
                                38.870387
                            ],
                            [
                                -77.006467,
                                38.870387
                            ],
                            [
                                -77.006467,
                                38.870454
                            ],
                            [
                                -77.006234,
                                38.87092
                            ],
                            [
                                -77.006131,
                                38.87105
                            ],
                            [
                                -77.006001,
                                38.871075
                            ],
                            [
                                -77.005839,
                                38.871082
                            ],
                            [
                                -77.005163,
                                38.871082
                            ],
                            [
                                -77.005001,
                                38.87109
                            ],
                            [
                                -77.004795,
                                38.871127
                            ],
                            [
                                -77.004207,
                                38.871127
                            ],
                            [
                                -77.004001,
                                38.871183
                            ],
                            [
                                -77.003509,
                                38.871429
                            ],
                            [
                                -77.003263,
                                38.87192
                            ],
                            [
                                -77.003114,
                                38.872033
                            ],
                            [
                                -77.003001,
                                38.872066
                            ],
                            [
                                -77.002797,
                                38.872124
                            ],
                            [
                                -77.002204,
                                38.872124
                            ],
                            [
                                -77.002001,
                                38.872257
                            ],
                            [
                                -77.001831,
                                38.87209
                            ],
                            [
                                -77.00117,
                                38.87209
                            ],
                            [
                                -77.001001,
                                38.872034
                            ],
                            [
                                -77.000882,
                                38.872039
                            ],
                            [
                                -77.00012,
                                38.872039
                            ],
                            [
                                -77.000001,
                                38.872046
                            ],
                            [
                                -76.999882,
                                38.872039
                            ],
                            [
                                -76.999119,
                                38.872039
                            ],
                            [
                                -76.999001,
                                38.872033
                            ],
                            [
                                -76.998861,
                                38.87206
                            ],
                            [
                                -76.998208,
                                38.872128
                            ],
                            [
                                -76.998001,
                                38.872178
                            ],
                            [
                                -76.997808,
                                38.872114
                            ],
                            [
                                -76.997634,
                                38.87192
                            ],
                            [
                                -76.997475,
                                38.871446
                            ],
                            [
                                -76.997001,
                                38.871162
                            ],
                            [
                                -76.99677,
                                38.871152
                            ],
                            [
                                -76.996232,
                                38.871152
                            ],
                            [
                                -76.996001,
                                38.871143
                            ],
                            [
                                -76.995787,
                                38.871135
                            ],
                            [
                                -76.995215,
                                38.871135
                            ],
                            [
                                -76.995001,
                                38.871127
                            ],
                            [
                                -76.994802,
                                38.871119
                            ],
                            [
                                -76.994024,
                                38.870944
                            ],
                            [
                                -76.994001,
                                38.870942
                            ],
                            [
                                -76.993981,
                                38.87094
                            ],
                            [
                                -76.993936,
                                38.87092
                            ],
                            [
                                -76.993405,
                                38.870516
                            ],
                            [
                                -76.993001,
                                38.870405
                            ],
                            [
                                -76.992657,
                                38.870577
                            ],
                            [
                                -76.992485,
                                38.87092
                            ],
                            [
                                -76.992207,
                                38.871126
                            ],
                            [
                                -76.992001,
                                38.871184
                            ],
                            [
                                -76.991756,
                                38.871165
                            ],
                            [
                                -76.991245,
                                38.871165
                            ],
                            [
                                -76.991001,
                                38.871149
                            ],
                            [
                                -76.990839,
                                38.871082
                            ],
                            [
                                -76.990745,
                                38.87092
                            ],
                            [
                                -76.990555,
                                38.870474
                            ],
                            [
                                -76.990516,
                                38.870405
                            ],
                            [
                                -76.990388,
                                38.86992
                            ],
                            [
                                -76.990541,
                                38.869461
                            ],
                            [
                                -76.991001,
                                38.86916
                            ],
                            [
                                -76.991207,
                                38.869126
                            ],
                            [
                                -76.99127,
                                38.86892
                            ],
                            [
                                -76.991268,
                                38.868653
                            ],
                            [
                                -76.991253,
                                38.868172
                            ],
                            [
                                -76.991251,
                                38.86792
                            ],
                            [
                                -76.991407,
                                38.867515
                            ],
                            [
                                -76.991358,
                                38.867278
                            ],
                            [
                                -76.99166,
                                38.867261
                            ],
                            [
                                -76.992001,
                                38.867062
                            ],
                            [
                                -76.992096,
                                38.867015
                            ],
                            [
                                -76.992133,
                                38.86692
                            ],
                            [
                                -76.992124,
                                38.866797
                            ],
                            [
                                -76.99207,
                                38.86599
                            ],
                            [
                                -76.992065,
                                38.86592
                            ],
                            [
                                -76.992054,
                                38.865868
                            ],
                            [
                                -76.992001,
                                38.865747
                            ],
                            [
                                -76.991856,
                                38.865776
                            ],
                            [
                                -76.991733,
                                38.86592
                            ],
                            [
                                -76.991403,
                                38.866322
                            ],
                            [
                                -76.991001,
                                38.866455
                            ],
                            [
                                -76.990536,
                                38.866455
                            ],
                            [
                                -76.990307,
                                38.866614
                            ],
                            [
                                -76.990001,
                                38.866613
                            ],
                            [
                                -76.989679,
                                38.866242
                            ],
                            [
                                -76.989127,
                                38.866046
                            ],
                            [
                                -76.989001,
                                38.86598
                            ],
                            [
                                -76.988852,
                                38.86607
                            ],
                            [
                                -76.988443,
                                38.866363
                            ],
                            [
                                -76.988001,
                                38.866509
                            ],
                            [
                                -76.987709,
                                38.866629
                            ],
                            [
                                -76.987176,
                                38.866746
                            ],
                            [
                                -76.987001,
                                38.8668
                            ],
                            [
                                -76.986898,
                                38.866817
                            ],
                            [
                                -76.986616,
                                38.86692
                            ],
                            [
                                -76.986761,
                                38.867161
                            ],
                            [
                                -76.987001,
                                38.867429
                            ],
                            [
                                -76.987137,
                                38.867785
                            ],
                            [
                                -76.987112,
                                38.86792
                            ],
                            [
                                -76.987117,
                                38.868036
                            ],
                            [
                                -76.987263,
                                38.868658
                            ],
                            [
                                -76.987271,
                                38.86892
                            ],
                            [
                                -76.987581,
                                38.86934
                            ],
                            [
                                -76.988001,
                                38.869509
                            ],
                            [
                                -76.988245,
                                38.869676
                            ],
                            [
                                -76.988321,
                                38.86992
                            ],
                            [
                                -76.988562,
                                38.87036
                            ],
                            [
                                -76.988553,
                                38.870473
                            ],
                            [
                                -76.988658,
                                38.87092
                            ],
                            [
                                -76.988727,
                                38.871194
                            ],
                            [
                                -76.989001,
                                38.871635
                            ],
                            [
                                -76.989175,
                                38.871746
                            ],
                            [
                                -76.989246,
                                38.87192
                            ],
                            [
                                -76.98925,
                                38.872169
                            ],
                            [
                                -76.98925,
                                38.872672
                            ],
                            [
                                -76.989253,
                                38.87292
                            ],
                            [
                                -76.989164,
                                38.873084
                            ],
                            [
                                -76.989001,
                                38.873172
                            ],
                            [
                                -76.988502,
                                38.873421
                            ],
                            [
                                -76.988252,
                                38.87392
                            ],
                            [
                                -76.988169,
                                38.874089
                            ],
                            [
                                -76.988001,
                                38.874202
                            ],
                            [
                                -76.987708,
                                38.874213
                            ],
                            [
                                -76.987294,
                                38.874213
                            ],
                            [
                                -76.987001,
                                38.874226
                            ],
                            [
                                -76.986538,
                                38.874457
                            ],
                            [
                                -76.986306,
                                38.87492
                            ],
                            [
                                -76.986194,
                                38.875113
                            ],
                            [
                                -76.986001,
                                38.875275
                            ],
                            [
                                -76.985627,
                                38.875295
                            ],
                            [
                                -76.985375,
                                38.875295
                            ],
                            [
                                -76.985001,
                                38.875317
                            ],
                            [
                                -76.984577,
                                38.875345
                            ],
                            [
                                -76.984425,
                                38.875345
                            ],
                            [
                                -76.984001,
                                38.875376
                            ],
                            [
                                -76.983638,
                                38.875558
                            ],
                            [
                                -76.983457,
                                38.87592
                            ],
                            [
                                -76.983218,
                                38.876138
                            ],
                            [
                                -76.983001,
                                38.876217
                            ],
                            [
                                -76.982691,
                                38.87623
                            ],
                            [
                                -76.982311,
                                38.87623
                            ],
                            [
                                -76.982001,
                                38.876244
                            ],
                            [
                                -76.981657,
                                38.876264
                            ],
                            [
                                -76.981344,
                                38.876264
                            ],
                            [
                                -76.981001,
                                38.876287
                            ],
                            [
                                -76.980559,
                                38.876363
                            ],
                            [
                                -76.980443,
                                38.876363
                            ],
                            [
                                -76.980001,
                                38.876478
                            ],
                            [
                                -76.979852,
                                38.876772
                            ],
                            [
                                -76.979153,
                                38.876768
                            ],
                            [
                                -76.979001,
                                38.876828
                            ],
                            [
                                -76.978849,
                                38.876768
                            ],
                            [
                                -76.978118,
                                38.876803
                            ],
                            [
                                -76.978001,
                                38.876497
                            ],
                            [
                                -76.977542,
                                38.87638
                            ],
                            [
                                -76.977209,
                                38.87592
                            ],
                            [
                                -76.977158,
                                38.875764
                            ],
                            [
                                -76.977001,
                                38.87549
                            ],
                            [
                                -76.976635,
                                38.875554
                            ],
                            [
                                -76.97607,
                                38.87592
                            ],
                            [
                                -76.976697,
                                38.876224
                            ],
                            [
                                -76.976662,
                                38.876581
                            ],
                            [
                                -76.976783,
                                38.87692
                            ],
                            [
                                -76.976759,
                                38.877163
                            ],
                            [
                                -76.97668,
                                38.877599
                            ],
                            [
                                -76.976653,
                                38.87792
                            ],
                            [
                                -76.976487,
                                38.878407
                            ],
                            [
                                -76.976001,
                                38.87879
                            ],
                            [
                                -76.975885,
                                38.878804
                            ],
                            [
                                -76.975465,
                                38.87892
                            ],
                            [
                                -76.975721,
                                38.8792
                            ],
                            [
                                -76.976001,
                                38.879387
                            ],
                            [
                                -76.976163,
                                38.879083
                            ],
                            [
                                -76.976711,
                                38.87921
                            ],
                            [
                                -76.977001,
                                38.879127
                            ],
                            [
                                -76.977189,
                                38.879108
                            ],
                            [
                                -76.977789,
                                38.879132
                            ],
                            [
                                -76.978001,
                                38.879116
                            ],
                            [
                                -76.978147,
                                38.879066
                            ],
                            [
                                -76.97826,
                                38.87892
                            ],
                            [
                                -76.978574,
                                38.878493
                            ],
                            [
                                -76.979001,
                                38.878361
                            ],
                            [
                                -76.979426,
                                38.878346
                            ],
                            [
                                -76.979563,
                                38.878358
                            ],
                            [
                                -76.980001,
                                38.878347
                            ],
                            [
                                -76.980415,
                                38.878506
                            ],
                            [
                                -76.980773,
                                38.87892
                            ],
                            [
                                -76.980794,
                                38.879127
                            ],
                            [
                                -76.981001,
                                38.879646
                            ],
                            [
                                -76.981203,
                                38.879718
                            ],
                            [
                                -76.98149,
                                38.87992
                            ],
                            [
                                -76.981362,
                                38.880281
                            ],
                            [
                                -76.981001,
                                38.880911
                            ],
                            [
                                -76.981,
                                38.880919
                            ],
                            [
                                -76.981,
                                38.88092
                            ],
                            [
                                -76.980999,
                                38.880922
                            ],
                            [
                                -76.980944,
                                38.881864
                            ],
                            [
                                -76.980921,
                                38.88192
                            ],
                            [
                                -76.980917,
                                38.882004
                            ],
                            [
                                -76.981001,
                                38.882097
                            ],
                            [
                                -76.981423,
                                38.882342
                            ],
                            [
                                -76.981521,
                                38.8824
                            ],
                            [
                                -76.982001,
                                38.88267
                            ],
                            [
                                -76.98224,
                                38.882682
                            ],
                            [
                                -76.982708,
                                38.882628
                            ],
                            [
                                -76.983001,
                                38.882638
                            ],
                            [
                                -76.983276,
                                38.882645
                            ],
                            [
                                -76.983897,
                                38.882817
                            ],
                            [
                                -76.984001,
                                38.882821
                            ],
                            [
                                -76.984063,
                                38.882859
                            ],
                            [
                                -76.984111,
                                38.88292
                            ],
                            [
                                -76.984666,
                                38.883255
                            ],
                            [
                                -76.985001,
                                38.883321
                            ],
                            [
                                -76.985447,
                                38.883367
                            ],
                            [
                                -76.985549,
                                38.883372
                            ],
                            [
                                -76.986001,
                                38.883423
                            ],
                            [
                                -76.986421,
                                38.8835
                            ],
                            [
                                -76.986801,
                                38.883721
                            ],
                            [
                                -76.987001,
                                38.883794
                            ],
                            [
                                -76.987061,
                                38.883861
                            ],
                            [
                                -76.98712,
                                38.88392
                            ],
                            [
                                -76.987583,
                                38.884338
                            ],
                            [
                                -76.988001,
                                38.8847
                            ],
                            [
                                -76.988133,
                                38.884789
                            ],
                            [
                                -76.988234,
                                38.88492
                            ],
                            [
                                -76.988319,
                                38.885239
                            ],
                            [
                                -76.988367,
                                38.885554
                            ],
                            [
                                -76.988504,
                                38.88592
                            ],
                            [
                                -76.988843,
                                38.886078
                            ],
                            [
                                -76.989001,
                                38.886122
                            ],
                            [
                                -76.989345,
                                38.886265
                            ],
                            [
                                -76.989578,
                                38.886343
                            ],
                            [
                                -76.990001,
                                38.88657
                            ],
                            [
                                -76.990299,
                                38.886622
                            ],
                            [
                                -76.990527,
                                38.88692
                            ],
                            [
                                -76.990737,
                                38.887185
                            ],
                            [
                                -76.991001,
                                38.887447
                            ],
                            [
                                -76.991291,
                                38.88763
                            ],
                            [
                                -76.991547,
                                38.88792
                            ],
                            [
                                -76.991439,
                                38.888359
                            ],
                            [
                                -76.991414,
                                38.888507
                            ],
                            [
                                -76.991324,
                                38.88892
                            ],
                            [
                                -76.991874,
                                38.889047
                            ],
                            [
                                -76.992001,
                                38.889163
                            ],
                            [
                                -76.992466,
                                38.889455
                            ],
                            [
                                -76.992908,
                                38.88992
                            ],
                            [
                                -76.992958,
                                38.889963
                            ],
                            [
                                -76.993001,
                                38.88999
                            ],
                            [
                                -76.993095,
                                38.890015
                            ],
                            [
                                -76.993771,
                                38.89015
                            ],
                            [
                                -76.994001,
                                38.890224
                            ],
                            [
                                -76.994458,
                                38.890377
                            ],
                            [
                                -76.994534,
                                38.890387
                            ],
                            [
                                -76.995001,
                                38.890687
                            ],
                            [
                                -76.995141,
                                38.890781
                            ],
                            [
                                -76.995332,
                                38.89092
                            ],
                            [
                                -76.995688,
                                38.891233
                            ],
                            [
                                -76.996001,
                                38.891462
                            ],
                            [
                                -76.996263,
                                38.891658
                            ],
                            [
                                -76.996704,
                                38.89192
                            ],
                            [
                                -76.996915,
                                38.892006
                            ],
                            [
                                -76.997001,
                                38.892076
                            ],
                            [
                                -76.997444,
                                38.892477
                            ],
                            [
                                -76.997887,
                                38.89292
                            ],
                            [
                                -76.997937,
                                38.892984
                            ],
                            [
                                -76.998001,
                                38.893076
                            ]
                        ]
                    ]
                ],
                "type": "MultiPolygon"
            },
            "type": "Feature"
        }
    ],
    "type": "FeatureCollection",
    "properties": {
        "id": "c691da77813f0c1602b920d59ab108cc"
    }
}